potatoscript/potatoConfig.py
python/CodeTemplate.py
python/pthonTemplate.py
python/pyTemplate.py
python/pypiTemplate.py
python/pysonTemplate.py
python/pythonTemplate.py
python/xTemplate.py
pysonTemplate-1.1.6.dist-info/METADATA
pysonTemplate-1.1.6.dist-info/WHEEL
pysonTemplate-1.1.6.dist-info/top_level.txt
pysonTemplate-1.1.6.dist-info/RECORD
