Metadata-Version: 2.1
Name: pysonTemplate
Version: 1.1.6
Summary: A simple Template for create python project
Author: ks lim
Author-email: kianseng.lim@sony.com
